tests/__init__.py
tests/test_utilities.py
tests/headers/__init__.py
tests/headers/test_headers.py
tests/http_helpers/__init__.py
tests/http_helpers/test_helpers.py
tests/order_builder/__init__.py
tests/order_builder/test_builder.py
tests/order_builder/test_helpers.py
tests/signing/__init__.py
tests/signing/test_eip712.py
tests/signing/test_hmac.py
tn_py_clob_client/__init__.py
tn_py_clob_client/client.py
tn_py_clob_client/clob_types.py
tn_py_clob_client/config.py
tn_py_clob_client/constants.py
tn_py_clob_client/endpoints.py
tn_py_clob_client/exceptions.py
tn_py_clob_client/signer.py
tn_py_clob_client/utilities.py
tn_py_clob_client/headers/__init__.py
tn_py_clob_client/headers/headers.py
tn_py_clob_client/http_helpers/__init__.py
tn_py_clob_client/http_helpers/helpers.py
tn_py_clob_client/order_builder/__init__.py
tn_py_clob_client/order_builder/builder.py
tn_py_clob_client/order_builder/constants.py
tn_py_clob_client/order_builder/helpers.py
tn_py_clob_client/signing/__init__.py
tn_py_clob_client/signing/eip712.py
tn_py_clob_client/signing/hmac.py
tn_py_clob_client/signing/model.py
tn_py_clob_client-0.23.1.dist-info/LICENSE
tn_py_clob_client-0.23.1.dist-info/METADATA
tn_py_clob_client-0.23.1.dist-info/WHEEL
tn_py_clob_client-0.23.1.dist-info/top_level.txt
tn_py_clob_client-0.23.1.dist-info/RECORD
